methodosintscan/__init__.py
methodosintscan/core/__init__.py
methodosintscan/core/datetime_utils.py
methodosintscan/core/pydantic_utilities.py
methodosintscan/core/serialization.py
methodosintscan/py.typed
methodosintscan/resources/__init__.py
methodosintscan/resources/common/__init__.py
methodosintscan/resources/common/resources/__init__.py
methodosintscan/resources/common/resources/dns/__init__.py
methodosintscan/resources/common/resources/dns/dns_record.py
methodosintscan/resources/common/resources/dns/dns_record_type.py
methodosintscan/resources/discover/__init__.py
methodosintscan/resources/discover/resources/__init__.py
methodosintscan/resources/discover/resources/asn/__init__.py
methodosintscan/resources/discover/resources/asn/resources/__init__.py
methodosintscan/resources/discover/resources/asn/resources/asn/__init__.py
methodosintscan/resources/discover/resources/asn/resources/asn/discover_asn_config.py
methodosintscan/resources/discover/resources/asn/resources/asn/discover_asn_lookup.py
methodosintscan/resources/discover/resources/asn/resources/asn/discover_asn_report.py
methodosintscan/resources/discover/resources/asn/resources/asn/discover_asn_result.py
methodosintscan/resources/discover/resources/cdn/__init__.py
methodosintscan/resources/discover/resources/cdn/resources/__init__.py
methodosintscan/resources/discover/resources/cdn/resources/cdn/__init__.py
methodosintscan/resources/discover/resources/cdn/resources/cdn/cdn_match.py
methodosintscan/resources/discover/resources/cdn/resources/cdn/cdn_provider.py
methodosintscan/resources/discover/resources/cdn/resources/cdn/cdn_provider_entry.py
methodosintscan/resources/discover/resources/cdn/resources/cdn/cdn_providers.py
methodosintscan/resources/discover/resources/cdn/resources/cdn/discover_cdn_config.py
methodosintscan/resources/discover/resources/cdn/resources/cdn/discover_cdn_report.py
methodosintscan/resources/discover/resources/cdn/resources/cdn/discover_cdn_result.py
methodosintscan-0.0.67.dist-info/METADATA
methodosintscan-0.0.67.dist-info/WHEEL
methodosintscan-0.0.67.dist-info/RECORD
